README.txt
setup.py
docs/HISTORY.txt
docs/INSTALL.txt
docs/LICENSE.GPL
docs/LICENSE.txt
kss/__init__.py
kss.demo.egg-info/PKG-INFO
kss.demo.egg-info/SOURCES.txt
kss.demo.egg-info/dependency_links.txt
kss.demo.egg-info/entry_points.txt
kss.demo.egg-info/namespace_packages.txt
kss.demo.egg-info/not-zip-safe
kss.demo.egg-info/requires.txt
kss.demo.egg-info/top_level.txt
kss/demo/EXTERNALS.TXT
kss/demo/__init__.py
kss/demo/configure.zcml
kss/demo/demoview.py
kss/demo/events.py
kss/demo/helpers.py
kss/demo/interfaces.py
kss/demo/kss.demo-configure.zcml
kss/demo/kss.demo-meta.zcml
kss/demo/meta.zcml
kss/demo/registry.py
kss/demo/resource.py
kss/demo/simplecontent.py
kss/demo/simplecontent_z3.py
kss/demo/version.txt
kss/demo/browser/__init__.py
kss/demo/browser/body_macros.pt
kss/demo/browser/configure.zcml
kss/demo/browser/demo.css
kss/demo/browser/header_macros.pt
kss/demo/browser/kss_demo_index.pt
kss/demo/browser/registry.py
kss/demo/browser/coresyntax/__init__.py
kss/demo/browser/coresyntax/configure.zcml
kss/demo/browser/coresyntax/demoview.py
kss/demo/browser/coresyntax/kss_selector_param.kss
kss/demo/browser/coresyntax/kss_selector_param.pt
kss/demo/browser/coresyntax/kss_url_param.kss
kss/demo/browser/coresyntax/kss_url_param.pt
kss/demo/browser/selectors/__init__.py
kss/demo/browser/selectors/configure.zcml
kss/demo/browser/selectors/selectors.kss
kss/demo/browser/selectors/selectors.pt
kss/demo/configfeature/README
kss/demo/configfeature/__init__.py
kss/demo/configfeature/configure.zcml
kss/demo/configfeature/directives.py
kss/demo/configfeature/fiveconfig.py
kss/demo/configfeature/fiveconfig.zcml
kss/demo/configfeature/meta.py
kss/demo/configfeature/meta.zcml
kss/demo/configfeature/metacore.zcml
kss/demo/configfeature/tests/__init__.py
kss/demo/configfeature/tests/__parent__.py
kss/demo/configfeature/tests/configtest.py
kss/demo/configfeature/tests/test_directive.py
kss/demo/configfeature/tests/test_fiveconfig.py
kss/demo/demo/__init__.py
kss/demo/demo/autoupdate.kss
kss/demo/demo/autoupdate.pt
kss/demo/demo/basic_commands.kss
kss/demo/demo/basic_commands.pt
kss/demo/demo/cancel_submit.kss
kss/demo/demo/cancel_submit.pt
kss/demo/demo/configure.zcml
kss/demo/demo/demo.css
kss/demo/demo/demoview.py
